simpler/__init__.py
simpler/connectors/__init__.py
simpler/connectors/_base.py
simpler/connectors/singer.py
simpler/entities.py
simpler/flows.py
simpler/interop/__init__.py
simpler/interop/duckdb.py
simpler/interop/github.py
simpler/naming.py
simpler/properties.py
simpler/rules.py
simpler/stack.py
simpler/stores/__init__.py
simpler/stores/_base.py
simpler/tables.py
simpler/transforms/__init__.py
simpler/transforms/_aggregate.py
simpler/transforms/inline.py
simpler/transforms/sql.py
simpler_data-0.0.0.dist-info/METADATA
simpler_data-0.0.0.dist-info/WHEEL
simpler_data-0.0.0.dist-info/RECORD
